{"medals":[{"name":"Corntastic!","desc":"Beat Bamber Heard's week","img":{"src":"medals","anim":"Bamber","fps":24}},{"name":"Shreddingly Good!","desc":"Beat Davey Synthwheel's week","img":{"src":"medals","anim":"Davey","fps":24}},{"name":"Bruh Moment","desc":"Beat Ronnie & Boris's week","img":{"src":"medals","anim":"BorisAndRonnie","fps":24}},{"name":"The Swindler","desc":"FC Swindled...","img":{"src":"medals","anim":"Swindler","fps":24}},{"name":"Genocidal Tendencies","desc":"Beat Judgement Farm 1 & 2","img":{"src":"medals","anim":"Judgement","fps":24}},{"name":"Secret Song 1","desc":"You found Squeaky Clean!\nIt now appears in freeplay (Under the 'Joke Songs' category)","img":{"src":"medals","anim":"squeaky","fps":24}},{"name":"Am I A Joke To You?","desc":"Found Main Menu secret... You can now visit Davey's Nightmares...","img":{"src":"medals","anim":"Joke","fps":24}},{"name":"Secret Song 2","desc":"You found Test Footage!\nIt now appears in freeplay (Under the 'Davey's Nightmare' category)","img":{"src":"medals","anim":"Test","fps":24}},{"name":"Friendship!","desc":"Play every song in the 'Collab Songs' category","img":{"src":"medals","anim":"Collabs","fps":24}},{"name":"Nostalgia","desc":"Play all Volume. 1 songs","img":{"src":"medals","anim":"Old","fps":24}}]}
