<?xml version="1.0" encoding="utf-8"?>
<TextureAtlas imagePath="borisfuck.png">
	<!-- Created with Adobe Animate version 19.2.1.408 -->
	<!-- http://www.adobe.com/products/animate.html -->
	<SubTexture name="boris_ddown instance 10000" x="0" y="0" width="344" height="298" frameX="-27" frameY="-51" frameWidth="371" frameHeight="349"/>
	<SubTexture name="boris_ddown instance 10001" x="0" y="0" width="344" height="298" frameX="-27" frameY="-51" frameWidth="371" frameHeight="349"/>
	<SubTexture name="boris_ddown instance 10002" x="344" y="0" width="343" height="327" frameX="-19" frameY="-22" frameWidth="371" frameHeight="349"/>
	<SubTexture name="boris_ddown instance 10003" x="344" y="0" width="343" height="327" frameX="-19" frameY="-22" frameWidth="371" frameHeight="349"/>
	<SubTexture name="boris_ddown instance 10004" x="687" y="0" width="350" height="344" frameX="-7" frameY="-5" frameWidth="371" frameHeight="349"/>
	<SubTexture name="boris_ddown instance 10005" x="687" y="0" width="350" height="344" frameX="-7" frameY="-5" frameWidth="371" frameHeight="349"/>
	<SubTexture name="boris_ddown instance 10006" x="1037" y="0" width="353" height="349" frameX="0" frameY="0" frameWidth="371" frameHeight="349"/>
	<SubTexture name="boris_ddown instance 10007" x="1037" y="0" width="353" height="349" frameX="0" frameY="0" frameWidth="371" frameHeight="349"/>
	<SubTexture name="boris_ddown instance 10008" x="1037" y="0" width="353" height="349" frameX="0" frameY="0" frameWidth="371" frameHeight="349"/>
	<SubTexture name="boris_ddown instance 10009" x="1037" y="0" width="353" height="349" frameX="0" frameY="0" frameWidth="371" frameHeight="349"/>
	<SubTexture name="boris_ddown instance 10010" x="1037" y="0" width="353" height="349" frameX="0" frameY="0" frameWidth="371" frameHeight="349"/>
	<SubTexture name="boris_ddown instance 10011" x="1037" y="0" width="353" height="349" frameX="0" frameY="0" frameWidth="371" frameHeight="349"/>
	<SubTexture name="boris_ddown instance 10012" x="1037" y="0" width="353" height="349" frameX="0" frameY="0" frameWidth="371" frameHeight="349"/>
	<SubTexture name="boris_ddown instance 10013" x="1037" y="0" width="353" height="349" frameX="0" frameY="0" frameWidth="371" frameHeight="349"/>
	<SubTexture name="boris_ddown instance 10014" x="1037" y="0" width="353" height="349" frameX="0" frameY="0" frameWidth="371" frameHeight="349"/>
	<SubTexture name="boris_idle instance 10000" x="1390" y="0" width="398" height="417" frameX="-29" frameY="-4" frameWidth="434" frameHeight="422"/>
	<SubTexture name="boris_idle instance 10001" x="1390" y="0" width="398" height="417" frameX="-29" frameY="-4" frameWidth="434" frameHeight="422"/>
	<SubTexture name="boris_idle instance 10002" x="0" y="417" width="418" height="421" frameX="-15" frameY="0" frameWidth="434" frameHeight="422"/>
	<SubTexture name="boris_idle instance 10003" x="0" y="417" width="418" height="421" frameX="-15" frameY="0" frameWidth="434" frameHeight="422"/>
	<SubTexture name="boris_idle instance 10004" x="418" y="417" width="429" height="416" frameX="-5" frameY="-6" frameWidth="434" frameHeight="422"/>
	<SubTexture name="boris_idle instance 10005" x="418" y="417" width="429" height="416" frameX="-5" frameY="-6" frameWidth="434" frameHeight="422"/>
	<SubTexture name="boris_idle instance 10006" x="847" y="417" width="423" height="415" frameX="-2" frameY="-7" frameWidth="434" frameHeight="422"/>
	<SubTexture name="boris_idle instance 10007" x="847" y="417" width="423" height="415" frameX="-2" frameY="-7" frameWidth="434" frameHeight="422"/>
	<SubTexture name="boris_idle instance 10008" x="1270" y="417" width="421" height="415" frameX="0" frameY="-7" frameWidth="434" frameHeight="422"/>
	<SubTexture name="boris_idle instance 10009" x="1270" y="417" width="421" height="415" frameX="0" frameY="-7" frameWidth="434" frameHeight="422"/>
	<SubTexture name="boris_idle instance 10010" x="0" y="838" width="418" height="415" frameX="0" frameY="-7" frameWidth="434" frameHeight="422"/>
	<SubTexture name="boris_idle instance 10011" x="0" y="838" width="418" height="415" frameX="0" frameY="-7" frameWidth="434" frameHeight="422"/>
	<SubTexture name="boris_idle instance 10012" x="0" y="838" width="418" height="415" frameX="0" frameY="-7" frameWidth="434" frameHeight="422"/>
	<SubTexture name="boris_idle instance 10013" x="0" y="838" width="418" height="415" frameX="0" frameY="-7" frameWidth="434" frameHeight="422"/>
	<SubTexture name="boris_idle instance 10014" x="0" y="838" width="418" height="415" frameX="0" frameY="-7" frameWidth="434" frameHeight="422"/>
	<SubTexture name="boris_leffty instance 10000" x="418" y="838" width="317" height="370" frameX="0" frameY="-29" frameWidth="332" frameHeight="399"/>
	<SubTexture name="boris_leffty instance 10001" x="418" y="838" width="317" height="370" frameX="0" frameY="-29" frameWidth="332" frameHeight="399"/>
	<SubTexture name="boris_leffty instance 10002" x="735" y="838" width="296" height="393" frameX="-23" frameY="-6" frameWidth="332" frameHeight="399"/>
	<SubTexture name="boris_leffty instance 10003" x="735" y="838" width="296" height="393" frameX="-23" frameY="-6" frameWidth="332" frameHeight="399"/>
	<SubTexture name="boris_leffty instance 10004" x="1031" y="838" width="275" height="396" frameX="-46" frameY="-3" frameWidth="332" frameHeight="399"/>
	<SubTexture name="boris_leffty instance 10005" x="1031" y="838" width="275" height="396" frameX="-46" frameY="-3" frameWidth="332" frameHeight="399"/>
	<SubTexture name="boris_leffty instance 10006" x="1306" y="838" width="261" height="399" frameX="-67" frameY="0" frameWidth="332" frameHeight="399"/>
	<SubTexture name="boris_leffty instance 10007" x="1306" y="838" width="261" height="399" frameX="-67" frameY="0" frameWidth="332" frameHeight="399"/>
	<SubTexture name="boris_leffty instance 10008" x="1567" y="838" width="261" height="398" frameX="-71" frameY="-1" frameWidth="332" frameHeight="399"/>
	<SubTexture name="boris_leffty instance 10009" x="1567" y="838" width="261" height="398" frameX="-71" frameY="-1" frameWidth="332" frameHeight="399"/>
	<SubTexture name="boris_leffty instance 10010" x="0" y="1253" width="261" height="398" frameX="-71" frameY="-1" frameWidth="332" frameHeight="399"/>
	<SubTexture name="boris_leffty instance 10011" x="0" y="1253" width="261" height="398" frameX="-71" frameY="-1" frameWidth="332" frameHeight="399"/>
	<SubTexture name="boris_leffty instance 10012" x="261" y="1253" width="261" height="398" frameX="-71" frameY="-1" frameWidth="332" frameHeight="399"/>
	<SubTexture name="boris_leffty instance 10013" x="261" y="1253" width="261" height="398" frameX="-71" frameY="-1" frameWidth="332" frameHeight="399"/>
	<SubTexture name="boris_leffty instance 10014" x="261" y="1253" width="261" height="398" frameX="-71" frameY="-1" frameWidth="332" frameHeight="399"/>
	<SubTexture name="boris_rright instance 10000" x="522" y="1253" width="413" height="401" frameX="-5" frameY="-3" frameWidth="418" frameHeight="404"/>
	<SubTexture name="boris_rright instance 10001" x="522" y="1253" width="413" height="401" frameX="-5" frameY="-3" frameWidth="418" frameHeight="404"/>
	<SubTexture name="boris_rright instance 10002" x="935" y="1253" width="397" height="404" frameX="-13" frameY="0" frameWidth="418" frameHeight="404"/>
	<SubTexture name="boris_rright instance 10003" x="935" y="1253" width="397" height="404" frameX="-13" frameY="0" frameWidth="418" frameHeight="404"/>
	<SubTexture name="boris_rright instance 10004" x="1332" y="1253" width="395" height="404" frameX="-2" frameY="0" frameWidth="418" frameHeight="404"/>
	<SubTexture name="boris_rright instance 10005" x="1332" y="1253" width="395" height="404" frameX="-2" frameY="0" frameWidth="418" frameHeight="404"/>
	<SubTexture name="boris_rright instance 10006" x="0" y="1657" width="396" height="404" frameX="0" frameY="0" frameWidth="418" frameHeight="404"/>
	<SubTexture name="boris_rright instance 10007" x="0" y="1657" width="396" height="404" frameX="0" frameY="0" frameWidth="418" frameHeight="404"/>
	<SubTexture name="boris_rright instance 10008" x="396" y="1657" width="395" height="404" frameX="0" frameY="0" frameWidth="418" frameHeight="404"/>
	<SubTexture name="boris_rright instance 10009" x="396" y="1657" width="395" height="404" frameX="0" frameY="0" frameWidth="418" frameHeight="404"/>
	<SubTexture name="boris_rright instance 10010" x="396" y="1657" width="395" height="404" frameX="0" frameY="0" frameWidth="418" frameHeight="404"/>
	<SubTexture name="boris_rright instance 10011" x="396" y="1657" width="395" height="404" frameX="0" frameY="0" frameWidth="418" frameHeight="404"/>
	<SubTexture name="boris_rright instance 10012" x="396" y="1657" width="395" height="404" frameX="0" frameY="0" frameWidth="418" frameHeight="404"/>
	<SubTexture name="boris_rright instance 10013" x="396" y="1657" width="395" height="404" frameX="0" frameY="0" frameWidth="418" frameHeight="404"/>
	<SubTexture name="boris_rright instance 10014" x="396" y="1657" width="395" height="404" frameX="0" frameY="0" frameWidth="418" frameHeight="404"/>
	<SubTexture name="boris_upper instance 10000" x="791" y="1657" width="444" height="425" frameX="-17" frameY="0" frameWidth="470" frameHeight="425"/>
	<SubTexture name="boris_upper instance 10001" x="791" y="1657" width="444" height="425" frameX="-17" frameY="0" frameWidth="470" frameHeight="425"/>
	<SubTexture name="boris_upper instance 10002" x="1235" y="1657" width="450" height="408" frameX="-20" frameY="-17" frameWidth="470" frameHeight="425"/>
	<SubTexture name="boris_upper instance 10003" x="1235" y="1657" width="450" height="408" frameX="-20" frameY="-17" frameWidth="470" frameHeight="425"/>
	<SubTexture name="boris_upper instance 10004" x="0" y="2082" width="456" height="405" frameX="-7" frameY="-20" frameWidth="470" frameHeight="425"/>
	<SubTexture name="boris_upper instance 10005" x="0" y="2082" width="456" height="405" frameX="-7" frameY="-20" frameWidth="470" frameHeight="425"/>
	<SubTexture name="boris_upper instance 10006" x="456" y="2082" width="458" height="403" frameX="0" frameY="-22" frameWidth="470" frameHeight="425"/>
	<SubTexture name="boris_upper instance 10007" x="456" y="2082" width="458" height="403" frameX="0" frameY="-22" frameWidth="470" frameHeight="425"/>
	<SubTexture name="boris_upper instance 10008" x="914" y="2082" width="456" height="403" frameX="0" frameY="-22" frameWidth="470" frameHeight="425"/>
	<SubTexture name="boris_upper instance 10009" x="914" y="2082" width="456" height="403" frameX="0" frameY="-22" frameWidth="470" frameHeight="425"/>
	<SubTexture name="boris_upper instance 10010" x="914" y="2082" width="456" height="403" frameX="0" frameY="-22" frameWidth="470" frameHeight="425"/>
	<SubTexture name="boris_upper instance 10011" x="914" y="2082" width="456" height="403" frameX="0" frameY="-22" frameWidth="470" frameHeight="425"/>
	<SubTexture name="boris_upper instance 10012" x="914" y="2082" width="456" height="403" frameX="0" frameY="-22" frameWidth="470" frameHeight="425"/>
	<SubTexture name="boris_upper instance 10013" x="914" y="2082" width="456" height="403" frameX="0" frameY="-22" frameWidth="470" frameHeight="425"/>
	<SubTexture name="boris_upper instance 10014" x="914" y="2082" width="456" height="403" frameX="0" frameY="-22" frameWidth="470" frameHeight="425"/>
</TextureAtlas>
